fregger
