Metadata-Version: 1.1
Name: Fregger
Version: 0.10.6
Summary: Automatically generate Swagger docs for Flask-Restful.
Home-page: https://github.com/AristotleJunior/fregger
Author: rain
Author-email: rain@joymud.com
License: MIT
Keywords: flask,flask-restful,swagger,docs,automatically
Platform: any
Classifier: Development Status :: 4 - Beta
Classifier: Environment :: Web Environment
Classifier: Framework :: Flask
Classifier: Intended Audience :: Developers
Classifier: License :: OSI Approved :: MIT License
Classifier: Operating System :: OS Independent
Classifier: Natural Language :: English
Classifier: Programming Language :: Python :: 3
Classifier: Topic :: Internet :: WWW/HTTP :: Dynamic Content
Classifier: Topic :: Software Development :: Libraries :: Python Modules
